ionics/LICENSE
ionics/VERSION
ionics/__init__.py
ionics/start_gui.py
ionics/ddcs/__init__.py
ionics/ddcs/random_sampling.py
ionics/ddcs/voitkiv.py
ionics/gui/__init__.py
ionics/gui/cross_section_view.py
ionics/gui/dialogs.py
ionics/gui/fileview.py
ionics/gui/main.py
ionics/gui/mainwidget.py
ionics/gui/mainwindow.py
ionics/gui/plotcontainer.py
ionics/gui/plots.py
ionics/gui/plotview.py
ionics/gui/pyqt45.py
ionics/gui/test.py
ionics/material_data/Ar.py
ionics/material_data/H.py
ionics/material_data/H2.py
ionics/material_data/H2O.py
ionics/material_data/He.py
ionics/material_data/Kr.py
ionics/material_data/N2.py
ionics/material_data/Ne.py
ionics/material_data/O2.py
ionics/material_data/Xe.py
ionics/material_data/__init__.py
ionics/sdcs/__init__.py
ionics/sdcs/bethe.py
ionics/sdcs/binary_encounter.py
ionics/sdcs/voitkiv.py
ionics-0.2.3.dist-info/DESCRIPTION.rst
ionics-0.2.3.dist-info/METADATA
ionics-0.2.3.dist-info/RECORD
ionics-0.2.3.dist-info/WHEEL
ionics-0.2.3.dist-info/metadata.json
ionics-0.2.3.dist-info/top_level.txt
