Metadata-Version: 2.0
Name: ionics
Version: 0.2.3
Summary: This package contains various ionization cross section models.
Home-page: https://gitlab.com/IPMsim/Ionization-Cross-Sections
Author: Dominik Vilsmeier
Author-email: d.vilsmeier@gsi.de
License: GPL-3.0
Keywords: ionization
Platform: UNKNOWN
Classifier: Development Status :: 3 - Alpha
Classifier: License :: OSI Approved :: GNU General Public License v3 (GPLv3)
Classifier: Programming Language :: Python :: 2.7
Classifier: Programming Language :: Python :: 3.5
Classifier: Topic :: Scientific/Engineering :: Physics
Requires-Dist: numpy
Requires-Dist: scipy
